pdequinox/__init__.py
pdequinox/_hierarchical.py
pdequinox/_sample_data.py
pdequinox/_sequential.py
pdequinox/_utils.py
pdequinox/arch/__init__.py
pdequinox/arch/_classic_fno.py
pdequinox/arch/_classic_res_net.py
pdequinox/arch/_classic_u_net.py
pdequinox/arch/_conv_net.py
pdequinox/arch/_dilated_res_net.py
pdequinox/arch/_mlp.py
pdequinox/arch/_modern_res_net.py
pdequinox/arch/_modern_u_net.py
pdequinox/blocks/__init__.py
pdequinox/blocks/_base_block.py
pdequinox/blocks/_classic_double_conv_block.py
pdequinox/blocks/_classic_res_block.py
pdequinox/blocks/_classic_spectral_block.py
pdequinox/blocks/_dilated_res_block.py
pdequinox/blocks/_linear_channel_adjust_block.py
pdequinox/blocks/_linear_conv_block.py
pdequinox/blocks/_linear_conv_down_block.py
pdequinox/blocks/_linear_conv_up_block.py
pdequinox/blocks/_modern_res_block.py
pdequinox/conv/__init__.py
pdequinox/conv/_conv.py
pdequinox/conv/_physics_conv.py
pdequinox/conv/_pointwise_linear_conv.py
pdequinox/conv/_spectral_conv.py
pdequinox-0.1.2.dist-info/LICENSE.txt
pdequinox-0.1.2.dist-info/METADATA
pdequinox-0.1.2.dist-info/WHEEL
pdequinox-0.1.2.dist-info/top_level.txt
pdequinox-0.1.2.dist-info/RECORD
