Metadata-Version: 2.1
Name: pdequinox
Version: 0.1.2
Summary: Neural PDE Emulator Architectures in JAX built on top of Equinox.
Author: Felix Koehler
Project-URL: repository, https://github.com/Ceyron/pdequinox
Keywords: jax,sciml,deep-learning,pde,neural operator
Requires-Python: ~=3.10
License-File: LICENSE.txt
Requires-Dist: jax >=0.4.13
Requires-Dist: jaxtyping >=0.2.20
Requires-Dist: typing-extensions >=4.5.0
Requires-Dist: equinox >=0.11.3
